bayinf/__init__.py
bayinf/plot.py
bayinf/version.py
bayinf-0.1.0.dist-info/METADATA
bayinf-0.1.0.dist-info/WHEEL
bayinf-0.1.0.dist-info/top_level.txt
bayinf-0.1.0.dist-info/RECORD
