Metadata-Version: 2.1
Name: bayinf
Version: 0.1.0
Summary: Bayesian Inference
Home-page: http://github.com/zhiqingxiao/bayinf/
Author: Zhiqing Xiao
Author-email: xzq.xiaozhiqing@gmail.com
Classifier: Programming Language :: Python
Classifier: Intended Audience :: Science/Research
